log_data/__init__.py
log_data/custom_logger.py
log_data/notion.py
log_data/test.py
log_data/utility.py
log_data-1.2.0.dist-info/METADATA
log_data-1.2.0.dist-info/WHEEL
log_data-1.2.0.dist-info/entry_points.txt
log_data-1.2.0.dist-info/top_level.txt
log_data-1.2.0.dist-info/RECORD
